{"ongoing_trials": {}, "hyperparameters": {"space": [{"class_name": "Int", "config": {"name": "lstm_units", "default": null, "conditions": [], "min_value": 32, "max_value": 96, "step": 16, "sampling": "linear"}}, {"class_name": "Int", "config": {"name": "dense_units", "default": null, "conditions": [], "min_value": 32, "max_value": 96, "step": 16, "sampling": "linear"}}, {"class_name": "Float", "config": {"name": "learning_rate", "default": 1e-05, "conditions": [], "min_value": 1e-05, "max_value": 0.0001, "step": null, "sampling": "log"}}], "values": {"lstm_units": 32, "dense_units": 32, "learning_rate": 1e-05}}, "start_order": ["0", "1", "2", "3", "4"], "end_order": ["0", "1", "2", "3", "4"], "run_times": {"0": 1, "1": 1, "2": 1, "3": 1, "4": 1}, "retry_queue": [], "seed": 152, "seed_state": 167, "tried_so_far": ["8e50a4f0651962e01a30ecdfbdb5a45a", "7c8937436ec659aa028207a612f412e3", "a2c3b2bee24f38af50783393695f6d82", "b5608eb318adbc666d89764eabce37e4", "f0d22580a5d4a90432fbe213f32f5a04"], "id_to_hash": {"0": "7c8937436ec659aa028207a612f412e3", "1": "a2c3b2bee24f38af50783393695f6d82", "2": "f0d22580a5d4a90432fbe213f32f5a04", "3": "8e50a4f0651962e01a30ecdfbdb5a45a", "4": "b5608eb318adbc666d89764eabce37e4"}, "display": {"search_start": "2024-10-04T22:14:36.487487", "trial_start": {"0": "2024-10-04T22:14:36.487487", "1": "2024-10-04T22:15:57.400604", "2": "2024-10-04T22:17:17.480539", "3": "2024-10-04T22:18:38.271559", "4": "2024-10-04T22:19:57.491129"}, "trial_number": {"0": 1, "1": 2, "2": 3, "3": 4, "4": 5}}}