{"trial_id": "2", "hyperparameters": {"space": [{"class_name": "Int", "config": {"name": "lstm_units", "default": null, "conditions": [], "min_value": 32, "max_value": 128, "step": 16, "sampling": "linear"}}, {"class_name": "Int", "config": {"name": "dense_units", "default": null, "conditions": [], "min_value": 32, "max_value": 128, "step": 16, "sampling": "linear"}}, {"class_name": "Float", "config": {"name": "learning_rate", "default": 1e-06, "conditions": [], "min_value": 1e-06, "max_value": 0.001, "step": null, "sampling": "log"}}], "values": {"lstm_units": 96, "dense_units": 80, "learning_rate": 9.831808697166114e-05}}, "metrics": {"metrics": {"loss": {"direction": "min", "observations": [{"value": [0.004281819798052311], "step": 9}]}, "mae": {"direction": "min", "observations": [{"value": [0.035553038120269775], "step": 9}]}, "val_loss": {"direction": "min", "observations": [{"value": [0.010493281297385693], "step": 9}]}, "val_mae": {"direction": "min", "observations": [{"value": [0.0598001591861248], "step": 9}]}}}, "score": 0.010493281297385693, "best_step": 9, "status": "COMPLETED", "message": null}